reddit_comment_scraper/__init__.py
reddit_comment_scraper-2.0.5.dist-info/DESCRIPTION.rst
reddit_comment_scraper-2.0.5.dist-info/entry_points.txt
reddit_comment_scraper-2.0.5.dist-info/METADATA
reddit_comment_scraper-2.0.5.dist-info/metadata.json
reddit_comment_scraper-2.0.5.dist-info/RECORD
reddit_comment_scraper-2.0.5.dist-info/top_level.txt
reddit_comment_scraper-2.0.5.dist-info/WHEEL
