Metadata-Version: 2.0
Name: reddit-comment-scraper
Version: 2.0.5
Summary: A simple Reddit-scraping script
Home-page: https://github.com/jfarmer/reddit_comment_scraper
Author: Jesse Farmer
Author-email: jesse@20bits.com
License: MIT
Platform: UNKNOWN
Classifier: Development Status :: 4 - Beta
Classifier: Natural Language :: English
Classifier: Intended Audience :: Science/Research
Classifier: License :: OSI Approved :: MIT License
Classifier: Programming Language :: Python :: 2.7
Classifier: Environment :: Console
Classifier: Operating System :: POSIX
Classifier: Operating System :: MacOS :: MacOS X
Classifier: Operating System :: Microsoft :: Windows :: Windows 7
Classifier: Operating System :: Microsoft :: Windows :: Windows Vista
Requires-Dist: unicodecsv (==0.9.4)
Requires-Dist: praw (==2.1.19)
